pulumi_yandex_marketmaker/__init__.py
pulumi_yandex_marketmaker/_inputs.py
pulumi_yandex_marketmaker/_utilities.py
pulumi_yandex_marketmaker/alb_backend_group.py
pulumi_yandex_marketmaker/alb_http_router.py
pulumi_yandex_marketmaker/alb_load_balancer.py
pulumi_yandex_marketmaker/alb_target_group.py
pulumi_yandex_marketmaker/alb_virtual_host.py
pulumi_yandex_marketmaker/api_gateway.py
pulumi_yandex_marketmaker/audit_trails_trail.py
pulumi_yandex_marketmaker/backup_policy.py
pulumi_yandex_marketmaker/backup_policy_bindings.py
pulumi_yandex_marketmaker/cdn_origin_group.py
pulumi_yandex_marketmaker/cdn_resource.py
pulumi_yandex_marketmaker/cm_certificate.py
pulumi_yandex_marketmaker/cm_certificate_iam_binding.py
pulumi_yandex_marketmaker/cm_certificate_iam_member.py
pulumi_yandex_marketmaker/compute_disk.py
pulumi_yandex_marketmaker/compute_disk_placement_group.py
pulumi_yandex_marketmaker/compute_filesystem.py
pulumi_yandex_marketmaker/compute_gpu_cluster.py
pulumi_yandex_marketmaker/compute_image.py
pulumi_yandex_marketmaker/compute_instance.py
pulumi_yandex_marketmaker/compute_instance_group.py
pulumi_yandex_marketmaker/compute_placement_group.py
pulumi_yandex_marketmaker/compute_snapshot.py
pulumi_yandex_marketmaker/compute_snapshot_schedule.py
pulumi_yandex_marketmaker/container_registry.py
pulumi_yandex_marketmaker/container_registry_iam_binding.py
pulumi_yandex_marketmaker/container_registry_ip_permission.py
pulumi_yandex_marketmaker/container_repository.py
pulumi_yandex_marketmaker/container_repository_iam_binding.py
pulumi_yandex_marketmaker/container_repository_lifecycle_policy.py
pulumi_yandex_marketmaker/dataproc_cluster.py
pulumi_yandex_marketmaker/datatransfer_endpoint.py
pulumi_yandex_marketmaker/datatransfer_transfer.py
pulumi_yandex_marketmaker/dns_recordset.py
pulumi_yandex_marketmaker/dns_zone.py
pulumi_yandex_marketmaker/dns_zone_iam_binding.py
pulumi_yandex_marketmaker/function.py
pulumi_yandex_marketmaker/function_iam_binding.py
pulumi_yandex_marketmaker-0.161.6.dist-info/METADATA
pulumi_yandex_marketmaker-0.161.6.dist-info/WHEEL
pulumi_yandex_marketmaker-0.161.6.dist-info/top_level.txt
pulumi_yandex_marketmaker-0.161.6.dist-info/RECORD
